{"stories":
[
    {
        "name": "行李问题_携带物品要求_充电宝",
        "intent": [
            "行李问题_携带物品要求_充电宝"
        ],
        "userinfo": {},
        "action": [
            [
                "reply",
                "1.充电宝必须是旅客个人自用携带。2.充电宝只能在手提行李中携带或随身携带，严禁在托运行李中携带。3.充电宝额定能量不超过100Wh,无需航空公司批准；额定能量超过100Wh但不超过160Wh，经航空公司批准后方可携带，但每名旅客不得携带超过两个充电宝。4.严禁携带额定能量超过160Wh的充电宝；严禁携带未标明额定能量同时也未能通过标注的其他参数计算得出额定能量的充电宝。5.不得在飞行过程中使用充电宝给电子设备充电。对于有启动开关的充电宝，在飞行过程中应始终关闭充电宝。"
            ]
        ]
    },
    {
        "name": "行李问题_行李丢失_理赔额度",
        "intent": [
            "行李问题_行李丢失_理赔额度"
        ],
        "userinfo": {},
        "action": [
            [
                "reply",
                "1.除办理声明价值的行李外，行李赔偿的最高限额为：国内航线每位旅客为每公斤100元人民币，国际航线每位旅客的最高限额是1131特别提款权，这是最大责任限额。2.如果您的物品折余价值低于最大限额，将得到按较低价值支付的赔偿。旅客随身携带物品，其保管责任为旅客本人。除能证明确系航空公司责任外，不予赔偿。"
            ]
        ]
    },
    {
        "name": "其他",
        "intent": [
            "其他"
        ],
        "userinfo": {},
        "action": [
            [
                "reply",
                "装运小动物的容器应符合下列要求：（一）能防止小动物破坏、逃逸和伸出容器以外损伤旅客、行李或货物。（二）保证空气流通，不致使小动物窒息。（三）能防止粪便渗溢，以免污染飞机、机上设备及其他物品。"
            ]
        ]
    },
    {
        "name": "行李问题_行李托运规则_行李尺寸问题",
        "intent": [
            "行李问题_行李托运规则_行李尺寸问题"
        ],
        "userinfo": {},
        "action": [
            [
                "reply",
                "1.国内航班：随身携带的手提行李总重量不要超过5公斤，每件物品的体积不得超过20×40×55厘米，超过规定件数、重量或体积的限制，航空公司将要求行李进行托运。2.国际航班：通常情况，手提行李总重量不要超过7公斤，每件行李体积不超过20×40×55厘米(三边之和不超过115厘米)。乘坐美加航线的旅客只能随身携带一件手提行李。（部分航空公司有特殊重量限制规定，请旅客留意机票上的提示，或向航空公司咨询）"
            ]
        ]
    },
    {
        "name": "票务问题_退票_因病退票要求",
        "intent": [
            "票务问题_退票_因病退票要求"
        ],
        "userinfo": {},
        "action": [
            [
                "reply",
                "1.国内航班如果因病要求退票，需提供医疗单位证明，始发地退还全部票款，经停地退还未使用航段的全部票款，不收取手续费。2.国内航班患病旅客的陪伴人员要求退票，不收取手续费3.国际航班旅客在旅途中患病，不能如期完成预定旅行的，承运人应当按规定延长该旅客及其陪同人员的客票有效期。4.国际航班旅客在旅途中死亡，承运人应当按规定延长该旅客陪同人员的客票有效期。（第3、4点出自《中国民用航空旅客行李国际运输规则》第十三条）"
            ]
        ]
    },
    {
        "name": "乘机流程问题_登机_国际出发流程",
        "intent": [
            "乘机流程问题_登机_国际出发流程"
        ],
        "userinfo": {},
        "action": [
            [
                "reply",
                "1.海关检查您有若物品申报时,请走红色通道,办理海关手续;如果没有,请走绿色通道。2.行李托运、换登机牌凭客票及本人有效身份证在指定值机柜台办理乘机和行李交运手续,领取登机牌。3.购买航空保险您可自行决定购买航空保险。4.边防检查请您确认出境卡是否填好,并连同护照、签证一并交边防检查站查验。5.安全检查为了飞行安全,您及随身携带行李物品必须接受安全检查。带入机内的行李要做x光机检查,旅客要走金属探测器门。6.候机及登机您可以根据登机牌所显示的登机口号在相应的候机厅候机休息,听广播温馨提示进行登机。"
            ]
        ]
    },
    {
        "name": "航班问题_航班延误_补偿规定",
        "intent": [
            "航班问题_航班延误_补偿规定"
        ],
        "userinfo": {},
        "action": [
            [
                "reply",
                "1.航班延误时，旅客享有知情权（有权获取信息）；2.选择权（可选择换乘同一航空公司的其他航班，也可选择换乘其他航空公司的航班，还可以选择退票）；3.索赔权（航空公司按照延误责任进行一定补偿，包括住宿、餐饮、交通等。国内航空公司的运输总条件中会包括是否对航班延误进行补偿；4.若给予补偿，会明确补偿条件、标准和方式等相关内容。"
            ]
        ]
    },
    {
        "name": "乘机流程问题_登机_国内出发流程",
        "intent": [
            "乘机流程问题_登机_国内出发流程"
        ],
        "userinfo": {},
        "action": [
            [
                "reply",
                "1.换登机牌、行李托运到达机场后,请到出发大厅指定的航司柜台凭本人有效身份证件按时办理乘机和行李交运手续,领取登机牌。2.购买航空保险您可自行决定是否购买保险。3.安全检查通过安全检查时,您应首先向工作人员出示登机牌,旅客要走金属探测器门。4.候机及登机您可以根据登机牌所显示的登机口号在相应的候机厅候机休息,听广播提示进行登机。"
            ]
        ]
    },
    {
        "name": "乘机流程问题_到达_国内到达流程",
        "intent": [
            "乘机流程问题_到达_国内到达流程"
        ],
        "userinfo": {},
        "action": [
            [
                "reply",
                "1.领取交运行李到达目的地后,请您确认航班号,到相应的行李转盘领取交运行李。行李多时,使用行李手推车比较方便。\"红帽子\"可为您提供行李搬运服务。2.进入到达大厅到达大厅接客处设有市区各大宾馆接待柜台和公交售票柜台。出租车和公交巴士站台位于国内到达出口处。"
            ]
        ]
    },
    {
        "name": "航班问题_航班延误_空中交通管制延误解释",
        "intent": [
            "航班问题_航班延误_空中交通管制延误解释"
        ],
        "userinfo": {},
        "action": [
            [
                "reply",
                "1.民航的航路并非广阔天空任我飞，而是在限定的空域范围内飞行的。2.民航飞机在空中就如同汽车在地面一样，会受到诸多因素的限制和影响，民航飞机是在有限的空间、有限的时间和有限的条件下起飞、降落和飞行的。3.部分繁忙机场空中交通处于超负荷运转，飞机起飞前往往会在地面滑行甚至等待较长时间。"
            ]
        ]
    },
    {
        "name": "航班问题_航班延误_合并航班解释",
        "intent": [
            "航班问题_航班延误_合并航班解释"
        ],
        "userinfo": {},
        "action": [
            [
                "reply",
                "1.取消航班、合并航班通常发生在因天气原因导致航班大面积延误时。2.航空公司取消、合并航班正是为了维护旅客利益。3.为避免前一段航班延误导致后面航班继续延误，使航班运行秩序尽快恢复，航空公司会选择取消或合并航班的方案。"
            ]
        ]
    },
    {
        "name": "航班问题_漏乘误机_漏乘误机政策解释",
        "intent": [
            "航班问题_漏乘误机_漏乘误机政策解释"
        ],
        "userinfo": {},
        "action": [
            [
                "reply",
                "1.如果是因为航空公司原因未能搭乘上指定的航班，航空公司会为您改签后续航班；2.如果是您自身原因造成漏乘，按旅客误机处理。"
            ]
        ]
    },
    {
        "name": "航班问题_飞机故障_飞机故障政策解释",
        "intent": [
            "航班问题_飞机故障_飞机故障政策解释"
        ],
        "userinfo": {},
        "action": [
            [
                "reply",
                "1.首先请旅客放心，飞机的安全系数是在不断提高的。2.维修人员、机组人员和先进的机载计算机也会随时监视着飞机的任何情况，凡对飞行安全构成威胁的问题都将在继续飞行之前解决。但例行维护有时无法保证飞机设备不会突然出现故障3.整个排除故障的过程是需要一定时间的，即使是一些小故障，是否能放行也要用一套严格的维修检测程序进行控制。这些都是为了确保飞行安全。"
            ]
        ]
    },
    {
        "name": "行李问题_行李托运规则_行李损坏丢失漏取问题",
        "intent": [
            "行李问题_行李托运规则_行李损坏丢失漏取问题"
        ],
        "userinfo": {},
        "action": [
            [
                "reply",
                "1.托运行李运输发生延误、破损或丢失，请在机场进港厅立刻与行李查询部门联系。须出示有效乘机凭证、行李牌和身份证件，填写《行李运输事故记录》，并对各项内容进行确认。2.托运行李发生损失的，至迟应当自收到托运行李之日起七日内向承运人提出异议；托运行李发生延误的，至迟应当自托运行李交付旅客之日起二十一日内向承运人提出异议。"
            ]
        ]
    },
    {
        "name": "乘机流程问题_到达_国际到达流程",
        "intent": [
            "乘机流程问题_到达_国际到达流程"
        ],
        "userinfo": {},
        "action": [
            [
                "reply",
                "1.卫生检疫您在飞机内如果得到检疫所发的卫生健康卡,请填写必要事项并交到卫生检疫站。2.边防检查请您确认入境卡是否填好,并连同护照、签证一并交边防检查站查验。3.领取交运行李确认航班号,使用行李推车比较方便。4.海关检查如果您携带的物品没有超过免税范围,走绿色通道(无申报通道)；超过或不清楚时请走红色通道(申报通道),接受检查或办理海关手续。5.进入到达大厅您可以在大厅接客处兑换人民币。到达大厅接客处设有市区各大宾馆接待柜台和公交售票柜台。出租车和公交巴士站台位于国际到达出口处。"
            ]
        ]
    },
    {
        "name": "航班问题_航班延误_跑道繁忙延误政策",
        "intent": [
            "航班问题_航班延误_跑道繁忙延误政策"
        ],
        "userinfo": {},
        "action": [
            [
                "reply",
                "1.由于机场跑道有限或空中交通太过繁忙，此时可能落地和起飞的飞机较多，飞机起飞前可能会在地面滑行甚至等待较长时间。2.正常流量控制一般是有预计时间的，机组会根据情况决定旅客登机时间。3.如果遇上空中交通管制则无法预计时间，可能随时解除管制，这就要求飞机预先做好起飞准备工作，所以可能会让旅客在机上等待。4.如果等待时间已经很长，又没有接到空管部门很明确的起飞消息，机组考虑到旅客舒适的问题，就有可能会让旅客下飞机到候机楼等待。5.当空中或目的地机场出现一些意外情况，也可能会发生旅客坐上飞机临近起飞不得已又滑回等待的情况。6.发生机上延误后，承运人应当每30分钟向旅客通告延误原因、预计延误时间等航班动态信息。7.机上延误超过2小时（含）的，应当为机上旅客提供饮用水和食品。8.机上延误超过3个小时（含）且无明确起飞时间的，承运人应当在不违反航空安全、安全保卫规定的情况下，安排旅客下飞机等待。"
            ]
        ]
    },
    {
        "name": "航班问题_延误或取消政策_航班延误或取消赔偿政策",
        "intent": [
            "航班问题_延误或取消政策_航班延误或取消赔偿政策"
        ],
        "userinfo": {},
        "action": [
            [
                "reply",
                "1.由于机务维护、航班调配、机组等航空公司自身原因，造成航班在始发地出港延误或者取消，航空公司会向旅客提供餐食或者住宿等服务。2.由于天气、突发事件、空中交通管制、安检以及旅客等非承运人原因，造成航班在始发地出港延误或者取消，承运人应当协助旅客安排餐食和住宿，费用由旅客自理。3.国内航班在经停地延误或者取消，无论何种原因，承运人均应当向经停旅客提供餐食或者住宿服务。4.国内航班发生备降，无论何种原因，承运人均应当向备降旅客提供餐食或者住宿服务。"
            ]
        ]
    },
    {
        "name": "航班问题_延误或取消政策_航班延误或取消食宿政策",
        "intent": [
            "航班问题_延误或取消政策_航班延误或取消食宿政策"
        ],
        "userinfo": {},
        "action": [
            [
                "reply",
                "1.由于机务维护、航班调配、机组等航空公司自身原因，造成航班在始发地出港延误或者取消，航空公司会向旅客提供餐食或者住宿等服务。2.由于天气、突发事件、空中交通管制、安检以及旅客等非航空公司原因，造成航班在始发地出港延误或者取消，航空公司会协助旅客安排餐食和住宿，费用由旅客自理。3.国内航班在经停地延误或者取消，无论何种原因，航空公司均会向经停旅客提供餐食或者住宿服务。4.国内航班发生备降，无论何种原因，航空公司均会向备降旅客提供餐食或者住宿服务。"
            ]
        ]
    },
    {
        "name": "行李问题_行李托运规则_行李托运规则",
        "intent": [
            "行李问题_行李托运规则_行李托运规则"
        ],
        "userinfo": {},
        "action": [
            [
                "reply",
                "1、国内托运行李的重量每件不能超过50公斤，体积为40×60×100厘米，超过上述规定的行李，须事先征得承运人的同意才能托运。（出自《中国民用航空旅客。行李国内运输规则》第三十七条）2、国际托运行李的重量和体积不得超过承运人规定，超过规定的托运行李应事先经承运人同意。（出自《中国民用航空旅客行李国际运输规则》第四十七条）3、旅行箱需要上锁，纸箱、编织袋需要打包。4、托运行李内请不要夹带现金、珠宝、有价证券、贵重物品和锂电池等易燃易爆物品5、建议您在托运的行李箱外拴挂或粘贴个人名签，以便行李运输发生问题时，方便查找。6、贵重物品、数码电子产品、易损坏、易腐物品等，不得作为托运行李或夹入行李内托运。"
            ]
        ]
    },
    {
        "name": "票务问题_机票查验_机票查验方式",
        "intent": [
            "票务问题_机票查验_机票查验方式"
        ],
        "userinfo": {},
        "action": [
            [
                "reply",
                "1、您购票后可拨打所乘航空公司服务电话，核实客票真假，并请了解客票是否处于正常可使用状态。2、电话验真：致电400-8158888；3、网站验真：登陆http://www.travelsky.com； 如不需打印行程单，请索要订座记录编号进行验证。4、短信验真：中国移动的用户发送英文字母JP到10669018，收到回复短信后，按照温馨提示输入13位电子票号进行操作，就可以检验机票真假。"
            ]
        ]
    },
    {
        "name": "乘机流程问题_其他_乘机安全",
        "intent": [
            "乘机流程问题_其他_乘机安全"
        ],
        "userinfo": {},
        "action": [
            [
                "reply",
                "1、酗酒、寻衅滋事、抢占座位、行李舱（架）；\n2、从飞机关闭舱门时刻起，至结束飞行打开舱门时刻止，不得开启和使用移动电话等主动发射无线电信号功能的便携式电子设备（不包括航空公司根据使用情况验证后决定认为使用时不会影响飞机导航和通讯系统的便携式电子设备）；\n3、当飞机在滑行过程中，请您不要离开座位，不要在客舱中来回走动，不要打开行李架拿取行李物品；\n4、不得盗窃、损坏或擅自移动救生设施、设备；"
            ]
        ]
    },
    {
        "name": "行李问题_携带物品要求_打火机",
        "intent": [
            "行李问题_携带物品要求_打火机"
        ],
        "userinfo": {},
        "action": [
            [
                "reply",
                "2008年4月7号，中国民航局发布公告，禁止旅客随身携带打火机、火柴乘坐民航班机（含国际/地区航班、国内航班），也不可以放在托运行李中托运。贵重或品牌打火机如来不及托运，可寄存安检部门。"
            ]
        ]
    },
    {
        "name": "乘机流程问题_其他_护照登机政策",
        "intent": [
            "乘机流程问题_其他_护照登机政策"
        ],
        "userinfo": {},
        "action": [
            [
                "reply",
                "2017年5月23日，民航局公安局专门下发通知，进一步明确旅客使用护照乘坐国内航班的相关问题。通知指出，中华人民共和国护照可以作为有效乘机身份证件，办理国内航班购票、值机、安检手续"
            ]
        ]
    },
    {
        "name": "乘机流程问题_其他_军人依法优先政策",
        "intent": [
            "乘机流程问题_其他_军人依法优先政策"
        ],
        "userinfo": {},
        "action": [
            [
                "reply",
                "2017年7月1日起，在全国81个民航机场开通“军人依法优先”通道，并鼓励其他机场根据自身情况酌情开通，为军人在值机、安检、登机等环节提供周到高效服务。"
            ]
        ]
    },
    {
        "name": "乘机流程问题_其他_机长职责",
        "intent": [
            "乘机流程问题_其他_机长职责"
        ],
        "userinfo": {},
        "action": [
            [
                "reply",
                "《中华人民共和国航空法》规定如下：民用航空器的操作由机长负责，机长在其职权范围内发布的命令，民用航空器所载人员都应当执行。飞行中，对于任何破坏民用航空器、扰乱民用航空器内秩序、危害民用航空器所载人员或者财产安全以及其他危及飞行安全的行为，在保证安全的前提下，机长有权采取必要的适当措施。"
            ]
        ]
    },
    {
        "name": "乘机流程问题_其他_乘务员职责",
        "intent": [
            "乘机流程问题_其他_乘务员职责"
        ],
        "userinfo": {},
        "action": [
            [
                "reply",
                "按照国际民航组织的规定，保证客舱安全是乘务员的首要责任。在飞机爬升、颠簸和降落过程中，乘务员必须坐在自己的座位上，系好安全带。在此阶段内乘务员会暂停客舱服务。"
            ]
        ]
    },
    {
        "name": "乘机流程问题_其他_办理临时乘机证明",
        "intent": [
            "乘机流程问题_其他_办理临时乘机证明"
        ],
        "userinfo": {},
        "action": [
            [
                "reply",
                "办理《乘坐中国民航飞机临时身份证明》的申办条件：具备下列材料之一者，可以申办《乘坐民航飞机临时身份证明》1、旅客的过期、破损身份证或临时身份证原件；2、旅客的户口簿原件及复印件；3、旅客的中华人民共和国机动车驾驶证。4、国内机场公安机关6个月内为旅客出具的完整的《乘坐民航飞机临时身份证明》原件。5、旅客户籍所在地公安机关出具的户籍证明原件或者传真件。"
            ]
        ]
    },
    {
        "name": "票务问题_客票预定_病残旅客条件",
        "intent": [
            "票务问题_客票预定_病残旅客条件"
        ],
        "userinfo": {},
        "action": [
            [
                "reply",
                "病残旅客是指由于身体或精神上的病态或缺陷，在上下飞机、飞行途中及在机场地面服务过程中无生活自理能力，需要他人予以单独照料或帮助的旅客。"
            ]
        ]
    },
    {
        "name": "票务问题_客票预定_病残旅客购票政策",
        "intent": [
            "票务问题_客票预定_病残旅客购票政策"
        ],
        "userinfo": {},
        "action": [
            [
                "reply",
                "病残旅客要事先在航空公司售票处提出特殊服务申请。重病旅客要提供医疗单位出具的适宜乘机的证明，经航空公司同意后方可购票。传染病患者、精神病患者或健康情况可危及自身或影响其他旅客安全的旅客，航空公司有权拒绝运输，希望您能够配合并予以理解。"
            ]
        ]
    },
    {
        "name": "票务问题_客票预定_航班超售政策",
        "intent": [
            "票务问题_客票预定_航班超售政策"
        ],
        "userinfo": {},
        "action": [
            [
                "reply",
                "超售是指超过航班最大允许座位数的销售行为。旅客购票后不去机场乘机或不能去机场乘机，这些空着的座位就浪费了。这样不仅给航空公司造成空座损失，也使需要乘机的旅客买不到客票，不能成行。为弥补因部分旅客临时取消乘机计划而造成的航班座位虚耗，满足更多旅客出行需求，航空公司有可能在部分容易出现座位虚耗的航班上适当超售。超售是国际航空界的通行做法。航空公司在超售时应对您履行告知义务，并应保证为您妥善安排后续航程。"
            ]
        ]
    },
    {
        "name": "行李问题_携带物品要求_枪支弹药",
        "intent": [
            "行李问题_携带物品要求_枪支弹药"
        ],
        "userinfo": {},
        "action": [
            [
                "reply",
                "乘坐飞机时禁止：枪支(含各种仿真玩具枪、微型发射器及各种类型的攻击性武器)、弹药、军械、警械、爆炸物品、易燃易爆物品、剧毒物品、放射性物品、腐蚀性物品、危险溶液及其他禁运物品带上飞机或夹在行李、货物中托运。凡携带或夹带上述物品的一经查出，立即移交公安机关处理。"
            ]
        ]
    },
    {
        "name": "行李问题_携带物品要求_化妆品",
        "intent": [
            "行李问题_携带物品要求_化妆品"
        ],
        "userinfo": {},
        "action": [
            [
                "reply",
                "乘坐国内航班的旅客一律禁止随身携带液态物品，但可办理交运，其包装应符合民航运输有关规定。您可以随身携带少量旅行自用的化妆品，每种化妆品限带一件，其容器容积不得超过100毫升，并应置于独立袋内，接受开瓶检查。（出自《消费者航空旅行指南》P28）国际地区航班每人可携带100毫升液态物品乘坐从中国境内机场始发的国际、地区航班的旅客，随身携带的液态物品每件容积不得超过100毫升。盛放液态物品的容器，应置于最大容积不超过1升的、可重新封口的透明塑料袋中。每位旅客每次仅允许携带一个透明塑料袋，超出部分应交运。（出自《消费者航空旅行指南》P28）"
            ]
        ]
    },
    {
        "name": "乘机流程问题_其他_残障乘客政策",
        "intent": [
            "乘机流程问题_其他_残障乘客政策"
        ],
        "userinfo": {},
        "action": [
            [
                "reply",
                "除安全和法律另有规定外，具备乘机条件的残疾人不会被拒绝运输。如需要特殊服务时，请事先向航空公司提出申请，航空公司会为您提供上、下飞机及衔接航班的协助服务。"
            ]
        ]
    },
    {
        "name": "行李问题_携带物品要求_管制刀具",
        "intent": [
            "行李问题_携带物品要求_管制刀具"
        ],
        "userinfo": {},
        "action": [
            [
                "reply",
                "除管制刀具以外的如水果刀、剃须刀等生活用刀、手术刀等专业刀具、化妆品，可以办理托运。如来不及托运，可以办理相关手续后，在规定时间内由安检部门代为保管。"
            ]
        ]
    },
    {
        "name": "乘机流程问题_其他_飞行时电子设备使用政策",
        "intent": [
            "乘机流程问题_其他_飞行时电子设备使用政策"
        ],
        "userinfo": {},
        "action": [
            [
                "reply",
                "从飞机关闭舱门时刻起，至结束飞行打开舱门时刻止，不得开启和使用移动电话等主动发射无线电信号功能的便携式电子设备（不包括航空公司根据使用情况验证后决定认为使用时不会影响飞机导航和通讯系统的便携式电子设备）（部分航空公司允许将手机调至飞行模式，旅客需在购票前提前与航司咨询确认）"
            ]
        ]
    },
    {
        "name": "票务问题_客票预定_残病特殊旅客购票政策",
        "intent": [
            "票务问题_客票预定_残病特殊旅客购票政策"
        ],
        "userinfo": {},
        "action": [
            [
                "reply",
                "对于无成人陪伴儿童、病残旅客、盲人、聋人、孕妇（怀孕32周以上）等特殊旅客，需经航空公司预先同意后才能购票。请详细了解客票的有关事宜，如特价票的适用条件和行李运输规定等。如您有特殊餐食需求请在购票时提出申请，建议您乘机前提前咨询航空公司"
            ]
        ]
    },
    {
        "name": "票务问题_客票预定_特殊旅客条件",
        "intent": [
            "票务问题_客票预定_特殊旅客条件"
        ],
        "userinfo": {},
        "action": [
            [
                "reply",
                "对于因身份、行为、年龄和身体状况等原因，在旅途中需特殊礼遇或照料并符合一定运输条件的旅客，如重要旅客、轮椅旅客、担架旅客、无成人陪伴儿童、老人、盲人、聋人、孕妇等特殊旅客，我们建议您乘机前提前咨询航空公司售票处。"
            ]
        ]
    },
    {
        "name": "票务问题_客票预定_儿童乘机政策",
        "intent": [
            "票务问题_客票预定_儿童乘机政策"
        ],
        "userinfo": {},
        "action": [
            [
                "reply",
                "儿童购票乘机需要凭户口本或者《医学出生证》，或者户口所在地公安机关出具的身份证明乘机。到了机场后需带着户口本等证件先到机场派出所给儿童开具一张临时登机证明。购票可以使用复印件，登机需要原件，并与购票时同一的相符的证件。根据民航有关规定，年满1—12周岁(含12周岁)的儿童乘坐飞机，须带有随家人的户口本办理乘机手续，过安全检查;12周岁以上(不含12周岁)至16周岁以下(不含16周岁)的少年乘坐飞机，须带有随家人的户口本、贴有本人照片的学生证办理乘机手续，过安全检查;16周岁(含16周岁)以上的少年均凭身份证乘坐飞机。已年满16周岁还未来得及办理身份证的少年乘坐飞机，可凭本人户口本、贴有本人照片的学生证、2张小二吋单人免冠照片到机场公安现场值班室办理临时登机许可证明（注：临时登机许可证明仅限当日当次航班有效）方可登机。"
            ]
        ]
    },
    {
        "name": "乘机流程问题_其他_故障维修时间",
        "intent": [
            "乘机流程问题_其他_故障维修时间"
        ],
        "userinfo": {},
        "action": [
            [
                "reply",
                "发生故障后，维修人员在查找故障原因过程中，无法知道到底需要多长时间，维修部门只能大致估计用时。检修中若发现新的故障或维修过程中出现某些意外情况，会导致时间延长。"
            ]
        ]
    },
    {
        "name": "乘机流程问题_其他_签证政策",
        "intent": [
            "乘机流程问题_其他_签证政策"
        ],
        "userinfo": {},
        "action": [
            [
                "reply",
                "购买国际机票，请您了解清楚前往国的签证制度，并在购票时向航空公司咨询。检查所持护照是否在有效期之内，以免出行时产生不必要的麻烦。"
            ]
        ]
    },
    {
        "name": "乘机流程问题_其他_乘机证件问题",
        "intent": [
            "乘机流程问题_其他_乘机证件问题"
        ],
        "userinfo": {},
        "action": [
            [
                "reply",
                "购票时，需提供乘机人准确有效的证件号码。请注意，此证件要与办理乘机手续和通过安全检查时的证件相同。网上购票，一定要认真填写并确认您的姓名、登机时使用的证件号码、乘机日期和航程等信息。客票是实名制，不得转让。"
            ]
        ]
    },
    {
        "name": "乘机流程问题_值机_值机时间问题",
        "intent": [
            "乘机流程问题_值机_值机时间问题"
        ],
        "userinfo": {},
        "action": [
            [
                "reply",
                "航空公司根据各机场、航站楼的设施和环境的不同，截止办理乘机手续的时间是不同的，请您提前向航空公司、机场了解相关信息，以免误机。"
            ]
        ]
    },
    {
        "name": "票务问题_客票预定_票价变动政策",
        "intent": [
            "票务问题_客票预定_票价变动政策"
        ],
        "userinfo": {},
        "action": [
            [
                "reply",
                "航空公司普遍采用收益管理系统进行机票销售管理，会发生旅客购票时价格随时变化的情况，此属正常现象。"
            ]
        ]
    },
    {
        "name": "票务问题_票价_伤残军人优惠",
        "intent": [
            "票务问题_票价_伤残军人优惠"
        ],
        "userinfo": {},
        "action": [
            [
                "reply",
                "航空公司要开放官网、直销柜台、销售代理人、OTA平台等所有的销售渠道，不得对优惠客票的销售地点进行限制"
            ]
        ]
    },
    {
        "name": "乘机流程问题_其他_孕妇乘机政策",
        "intent": [
            "乘机流程问题_其他_孕妇乘机政策"
        ],
        "userinfo": {},
        "action": [
            [
                "reply",
                "怀孕不足32周的孕妇，除医生诊断不宜乘机外，航空公司按普通旅客接受运输。怀孕超过32周不超过35周的孕妇，必须提供县级以上医疗单位出具的有“适宜乘机”字样的诊断证明书，方可乘机。诊断证明书应在乘机前7天内填开。须在航空公司售票处提出申请。怀孕超过35周的孕妇，航空公司不予承运。孕妇乘机有一定危险性，为了您的自身安全，如选择乘机，应如实向航空公司说明情况，如因未如实说明情况而出现意外，航空公司不会承担责任。"
            ]
        ]
    },
    {
        "name": "乘机流程问题_其他_机场截载时间",
        "intent": [
            "乘机流程问题_其他_机场截载时间"
        ],
        "userinfo": {},
        "action": [
            [
                "reply",
                "欢迎来访。因每家机场截载时间不一致，建议您拨打始发机场客服热线进行咨询。"
            ]
        ]
    },
    {
        "name": "乘机流程问题_其他_残疾旅客服务政策",
        "intent": [
            "乘机流程问题_其他_残疾旅客服务政策"
        ],
        "userinfo": {},
        "action": [
            [
                "reply",
                "除安全和法律另有规定外，具备乘机条件的残疾人不会被拒绝运输。如需要特殊服务时，请事先向航空公司提出申请，航空公司会为您提供上、下飞机及衔接航班的协助服务。具备乘机条件的残疾人需要承运人提供下列设备设施或服务时，应在定座时提出，最迟不能晚于航班离站时间前48小时；并应在普通旅客办理乘机手续截止前2小时在机场办理乘机手续。：1、 供航空器上使用的医用氧气；2、 托运电动轮椅；3、 提供机上专用窄型轮椅；4、 为具备乘机条件的残疾人团体提供服务；5、 携带服务犬进入客舱。"
            ]
        ]
    },
    {
        "name": "乘机流程问题_其他_病残旅客能否乘机",
        "intent": [
            "乘机流程问题_其他_病残旅客能否乘机"
        ],
        "userinfo": {},
        "action": [
            [
                "reply",
                "具有下列情况之一的旅客不予办理1、对安检中发现冒用他人身份证件或使用伪造、变造身份证件的旅客；2、外籍和港澳台地区的旅客；3、非申办旅客本人；4、根据申办人提供的材料经公安网络查实不符的或无法证实是旅客本人的；5、无法通过公安网络查询的旅客。 "
            ]
        ]
    },
    {
        "name": "乘机流程问题_其他_错乘政策",
        "intent": [
            "乘机流程问题_其他_错乘政策"
        ],
        "userinfo": {},
        "action": [
            [
                "reply",
                "旅客错乘飞机，航空公司应安排错乘旅客搭乘最早的航班飞往旅客客票上的目的地，票款不补不退。若由航空公司原因造成旅客错乘，如旅客要求退票，不收退票费。"
            ]
        ]
    },
    {
        "name": "航班问题_其他_误机政策",
        "intent": [
            "航班问题_其他_误机政策"
        ],
        "userinfo": {},
        "action": [
            [
                "reply",
                "旅客误机后，航空公司会依据旅客所购客票舱位等级所对应的客票限制条件来办理相应手续。一般的，折扣机票限制使用条件较多，大多不得签转退票。因此，您在购买机票时一定要了解清楚客票的使用限制条件，以免造成不必要的麻烦耽搁您的行程。"
            ]
        ]
    },
    {
        "name": "行李问题_行李托运规则_托运保价政策",
        "intent": [
            "行李问题_行李托运规则_托运保价政策"
        ],
        "userinfo": {},
        "action": [
            [
                "reply",
                "旅客在办理行李交运时，如认为航空公司的行李限额规定不足以保护其利益，可申请办理行李的声明价值。每件行李的声明价值最高限额为人民币8000元，航空公司对声明价值有异议而旅客又拒绝接受检查时，航空公司有权拒绝收运。"
            ]
        ]
    },
    {
        "name": "票务问题_票价_儿童票价政策",
        "intent": [
            "票务问题_票价_儿童票价政策"
        ],
        "userinfo": {},
        "action": [
            [
                "reply",
                "满两周岁不满十二周岁的儿童，按国内航线成人普通票价的50%计价，国际航线根据航线不同而有差异。未满两周岁的婴儿，使用成人普通票价10%的客票乘机，不单独提供座位"
            ]
        ]
    },
    {
        "name": "乘机流程问题_安检_安检安全解释",
        "intent": [
            "乘机流程问题_安检_安检安全解释"
        ],
        "userinfo": {},
        "action": [
            [
                "reply",
                "民航安全检查门和金属探测器都是通过严格检验，符合安全标准和旅客安全标准，发射磁场厚度很低，对心脏起搏器佩戴患者、体弱者、孕妇，磁场媒质和其他一些电子装置均无损害，广大乘机旅客可以放心通过安检。"
            ]
        ]
    },
    {
        "name": "乘机流程问题_其他_证件过期问题",
        "intent": [
            "乘机流程问题_其他_证件过期问题"
        ],
        "userinfo": {},
        "action": [
            [
                "reply",
                "民航局公安局温馨提醒旅客，居民身份证过期不能继续使用。若有效期满的，可以凭临时居民身份证或公安机关出具的贴有本人近期免冠证件照、并加盖户籍专用章、注明有效期的《申领居民身份证回执》作为有效乘机身份证件替代使用"
            ]
        ]
    },
    {
        "name": "乘机流程问题_其他_无成人陪伴儿童政策",
        "intent": [
            "乘机流程问题_其他_无成人陪伴儿童政策"
        ],
        "userinfo": {},
        "action": [
            [
                "reply",
                "年龄在五周岁至十二周岁的儿童需要单独乘机时，应在购票前向航空公司申请无人陪伴儿童服务。航空公司对每个航班上无人陪伴儿童数量有明确限制，为了确保旅行的顺利，请务必提前申请，航空公司将为您提供满意的服务。"
            ]
        ]
    },
    {
        "name": "乘机流程问题_其他_耳部不适缓解方法",
        "intent": [
            "乘机流程问题_其他_耳部不适缓解方法"
        ],
        "userinfo": {},
        "action": [
            [
                "reply",
                "您可以通过做吞咽动作、打哈欠、咀嚼食品或打喷嚏等方法缓解不适症状。 "
            ]
        ]
    },
    {
        "name": "行李问题_携带物品要求_可随身携带物品要求2",
        "intent": [
            "行李问题_携带物品要求_可随身携带物品要求2"
        ],
        "userinfo": {},
        "action": [
            [
                "reply",
                "您在旅行期间可以免费自行携带零星小件物品乘机。航空公司对体积及重量有限制。每人可携带一件物品，每件的体积不超过20×40×55厘米，重量不超过5公斤。头等舱旅客可以携带2件5公斤。打火机、液体、刀具等不得作为随身携带物品带上飞机。(部分航空公司有特殊重量限制规定，请旅客留意机票上的提示，或向航空公司咨询)"
            ]
        ]
    },
    {
        "name": "票务问题_退票_退款返回方式",
        "intent": [
            "票务问题_退票_退款返回方式"
        ],
        "userinfo": {},
        "action": [
            [
                "reply",
                "票款只能退给客票上列明的旅客本人。如委托他人办理，须提供旅客本人和受委托人的有效身份证件。如您持折扣客票，退票按航空公司的有关规定办理。"
            ]
        ]
    },
    {
        "name": "票务问题_客票预定_特价票政策",
        "intent": [
            "票务问题_客票预定_特价票政策"
        ],
        "userinfo": {},
        "action": [
            [
                "reply",
                "如果您购买了特价客票，请您一定要仔细了解航空公司的限制条件（一般是不得退票、不得更改、不得签转），以免造成不必要的损失。"
            ]
        ]
    },
    {
        "name": "行李问题_行李托运规则_行李超重政策",
        "intent": [
            "行李问题_行李托运规则_行李超重政策"
        ],
        "userinfo": {},
        "action": [
            [
                "reply",
                "如果您托运行李超过客票所规定的免费行李额，须交纳逾重行李费，并填开逾重行李票。逾重行李费率和计算方法按各航空公司规定办理。"
            ]
        ]
    },
    {
        "name": "行李问题_携带物品要求_液体物品",
        "intent": [
            "行李问题_携带物品要求_液体物品"
        ],
        "userinfo": {},
        "action": [
            [
                "reply",
                "如果您携带了不符合安全要求的液态或凝胶物品，这些物品及容器只能弃置。安检部门 不设立保管或储存服务。请将液体、凝胶及喷雾类物品放在托运行李内，以便顺利通过安全检查。 "
            ]
        ]
    },
    {
        "name": "票务问题_退票_经停站退票政策",
        "intent": [
            "票务问题_退票_经停站退票政策"
        ],
        "userinfo": {},
        "action": [
            [
                "reply",
                "如果您在航班经停地自动终止旅行，则该航班未使用航段的票款不退。"
            ]
        ]
    },
    {
        "name": "票务问题_退票_退票政策",
        "intent": [
            "票务问题_退票_退票政策"
        ],
        "userinfo": {},
        "action": [
            [
                "reply",
                "如果您在客票有效期内要求退票，凭有效身份证件，按航空公司的规定即可办理。电子客票凭行程单办理退票手续，如果您未曾打印行程单，可凭有效身份证件办理退票手续。"
            ]
        ]
    },
    {
        "name": "票务问题_其他_机票有效期",
        "intent": [
            "票务问题_其他_机票有效期"
        ],
        "userinfo": {},
        "action": [
            [
                "reply",
                "如您购买的是普通票价的客票，有效期自您实际出发之日起，一年内有效；如果客票未曾使用，则自填开客票之日起，一年内有效。折扣票的有效期，适用航空公司公布的条件，请务必注意。客票有效期的计算：从旅行开始或填开客票之日的次日零时起至有效期满之日的次日零时为止。"
            ]
        ]
    },
    {
        "name": "票务问题_客票预定_联程票",
        "intent": [
            "票务问题_客票预定_联程票"
        ],
        "userinfo": {},
        "action": [
            [
                "reply",
                "如需转乘航班才能到达目的地的旅客，全部航程均填列在一张或多张票号相连的客票上"
            ]
        ]
    },
    {
        "name": "票务问题_客票预定_婴儿乘机政策",
        "intent": [
            "票务问题_客票预定_婴儿乘机政策"
        ],
        "userinfo": {},
        "action": [
            [
                "reply",
                "如婴儿需要单独占用座位，则应购买儿童票。每位成人旅客只能携带一名婴儿，超过的人数请另行购买儿童票。"
            ]
        ]
    },
    {
        "name": "行李问题_携带物品要求_充电宝额定能量规定",
        "intent": [
            "行李问题_携带物品要求_充电宝额定能量规定"
        ],
        "userinfo": {},
        "action": [
            [
                "reply",
                "若锂电池、充电宝上没有直接标注额定能量Wh（瓦特小时），则锂电池、充电宝额定能量可按照以下方式进行换算:　　如果已知锂电池、充电宝的标称电压(V )和标称容量(Ah)，可以通过计算得到额定能量的数值：Wh= V x Ah　　标称电压和标称容量通常标记在锂电池、充电宝上。　　如果锂电池、充电宝上只标记有毫安时(mAh)，可将该数值除以1000得到安培小时(Ah) 。　　例如：锂电池、充电宝标称电压为3.7V，标称容量为760 mAh ，其额定能量为：760 mAh ÷ 1000 = 0.76Ah；3.7V×0.76Ah=2.9Wh"
            ]
        ]
    },
    {
        "name": "行李问题_携带物品要求_锂电池",
        "intent": [
            "行李问题_携带物品要求_锂电池"
        ],
        "userinfo": {},
        "action": [
            [
                "reply",
                "可作为手提行李携带登机的锂电池额定能量值不得超过100Wh（瓦特小时）。超过100Wh但不超过160Wh的，经航空公司批准后可以装在交运行李或手提行李中的设备上。超过160Wh的锂电池严禁携带。经航空公司批准的100 -160Wh的备用锂电池只能携带两个。"
            ]
        ]
    },
    {
        "name": "航班问题_其他_航班取消欺诈短信",
        "intent": [
            "航班问题_其他_航班取消欺诈短信"
        ],
        "userinfo": {},
        "action": [
            [
                "reply",
                "收到不明号码发送的短信，短信内容为旅客所要乘坐的航班有变动，要求旅客联系他们提供的客服电话进行机票变更与退票业务，并需要收取手续费。多家航空公司均发出“防范欺诈短信的重要提示”，提醒旅客警惕不法分子冒用航空公司名义向旅客发送 “航班取消” “航班起飞时刻发生变动”的欺诈短信，以免上当受骗。对航班信息如有任何疑问，可联系航空公司客服电话进行确认"
            ]
        ]
    },
    {
        "name": "乘机流程问题_其他_小桌板遮光板解释",
        "intent": [
            "乘机流程问题_其他_小桌板遮光板解释"
        ],
        "userinfo": {},
        "action": [
            [
                "reply",
                "收起小桌板，调直座椅靠背是为了应急撤离情况下，减少对旅客的人身伤害。拉开遮光板，是为了应急情况下，及时查看客舱外情况，便于迅速撤离。"
            ]
        ]
    },
    {
        "name": "行李问题_携带物品要求_携带药品规定",
        "intent": [
            "行李问题_携带物品要求_携带药品规定"
        ],
        "userinfo": {},
        "action": [
            [
                "reply",
                "糖尿病患者或其他患者携带必需的液态药品，经安全检查确认无疑后，可根据飞行时间适量携带，超量部分必须托运。携带液态药品时最好出具医疗机构的相关证明。"
            ]
        ]
    },
    {
        "name": "票务问题_客票预定_特种票价",
        "intent": [
            "票务问题_客票预定_特种票价"
        ],
        "userinfo": {},
        "action": [
            [
                "reply",
                "特种票价通常分为两类：适用于政府规定的特定人群，如革命伤残军人和因公致残的人民警察等。在签转、变更和退票等方面的限制很少。航空公司根据市场淡旺季、购票人数、购票时间的早晚等情况推出的适用于经济舱的票价，通常称折扣客票，在购买此种客票时，请您务必了解该客票相关的限制条件。"
            ]
        ]
    },
    {
        "name": "航班问题_航班延误_航班因天气延误解释",
        "intent": [
            "航班问题_航班延误_航班因天气延误解释"
        ],
        "userinfo": {},
        "action": [
            [
                "reply",
                "天气原因造成延误有多重情况，出发机场、目的机场或航路天气状况不佳均有可能导致延误，例如：1.出发机场天气原因导致航班无法正常起飞降落，可能会造成延误。2.目的机场天气原因，即使目的城市天气状况良好也存在机场周边局部天气状况不好，不适宜飞机降落，如果在机场起飞和降落航路附近覆盖有低云、雷雨区，也不满足飞机起飞条件，也会导致航班延误。为了确保飞行安全，飞机即使处在自动降落状况，在降落前的高度，飞行员也必须完全能看见跑道及地面状况，如果此时无法看见跑道，是不允许降落的。3.若出发机场和目的机场天气状况均良好，但飞机飞行航旅气象状况不宜飞越，比如雷雨区无法通过。飞机往往只能在地面等待。一旦在狭窄的航路上出现雷雨区等状况，有时可采取绕过雷雨区的方式通过，但出于飞行安全和国防需要，民航航路是严格受限的，可绕飞、回旋的余地很小，雷雨区较大时，此方法就行不通了。"
            ]
        ]
    },
    {
        "name": "乘机流程问题_其他_紧急出口座位规定",
        "intent": [
            "乘机流程问题_其他_紧急出口座位规定"
        ],
        "userinfo": {},
        "action": [
            [
                "reply",
                "通常紧急出口座位不允许安排老、弱、病、残、孕、幼等旅客就座，更不允许放置任何行李物品。当您的座位在紧急出口，且身体状况不符合要求时，应主动与乘务员说明，或请您配合乘务人员进行座位调整。"
            ]
        ]
    },
    {
        "name": "行李问题_行李托运规则_托运办理流程",
        "intent": [
            "行李问题_行李托运规则_托运办理流程"
        ],
        "userinfo": {},
        "action": [
            [
                "reply",
                "托运办理流程：1、如有托运行李，建议您提前2小时到机场办理托运手续。2、带好托运行李、有效证件、到相应航司值机柜台办理3、行李如果超重需要补缴逾重行李费办理自助行李托运的要求（乘客、行李件数、重量等条件），具体建议您咨询机场旅客服务中心或航司官网。"
            ]
        ]
    },
    {
        "name": "行李问题_行李托运规则_托运办理时间",
        "intent": [
            "行李问题_行李托运规则_托运办理时间"
        ],
        "userinfo": {},
        "action": [
            [
                "reply",
                "托运办理时间：1、建议您提前2小时到达机场办理行李托运。2、目前国内出发航班截止办理乘机手续时间一般为航班计划起飞前30—45分钟，具体请以机场规定为准若转机遇到行李托运问题，建议您咨询机场旅客服务中心"
            ]
        ]
    },
    {
        "name": "航班问题_其他_流量控制解释",
        "intent": [
            "航班问题_其他_流量控制解释"
        ],
        "userinfo": {},
        "action": [
            [
                "reply",
                "为了保证飞行安全，在航班流量较大的航路或机场，空中交通管制部门为避免各个飞机之间出现危险接近或空中相撞，对飞机的流量进行控制。或由于机场繁忙，跑道有限，飞机排队起飞或目的地机场流量繁忙，始发机场受到控制。"
            ]
        ]
    },
    {
        "name": "行李问题_行李托运规则_动物托运收费政策",
        "intent": [
            "行李问题_行李托运规则_动物托运收费政策"
        ],
        "userinfo": {},
        "action": [
            [
                "reply",
                "小动物及其容器的重量应按逾重行李费的标准单独收费。"
            ]
        ]
    },
    {
        "name": "行李问题_行李托运规则_动物托运规定",
        "intent": [
            "行李问题_行李托运规则_动物托运规定"
        ],
        "userinfo": {},
        "action": [
            [
                "reply",
                "小动物是指家庭饲养的猫、狗等玩赏宠物。（野生动物和具有形体怪异或者易于伤人等特性的动物如蛇等，不属于小动物）旅客携带小动物必须在定座或购票时提出，并提供动物检疫证明，经航空公司同意后方可托运。旅客应在乘机的当日，按航空公司指定的时间，将小动物自行运到机场办理托运手续。国际航班还必须具备中国和运输过程中有关国家运输小动物出入境或过境所需的有效证件。"
            ]
        ]
    },
    {
        "name": "行李问题_行李托运规则_托运延误政策",
        "intent": [
            "行李问题_行李托运规则_托运延误政策"
        ],
        "userinfo": {},
        "action": [
            [
                "reply",
                "因航空公司原因使旅客的托运行李未能与旅客同机到达，造成旅途生活不便时，在经停地或目的地机场，旅客可领取规定的临时生活用品补偿费。（来源：中国民用航空局官网-航旅指南-行李）"
            ]
        ]
    },
    {
        "name": "票务问题_客票预定_中转联程政策",
        "intent": [
            "票务问题_客票预定_中转联程政策"
        ],
        "userinfo": {},
        "action": [
            [
                "reply",
                "由航空公司之间或独自的航班通过中转的方式到达目的地的旅行方式叫做中转联程，也叫无缝转接。中转时航班最短衔接时间为45分钟-72小时。由于中转联程的价格比正常直达票价低很多,所以倍受旅客的青睐,是自费商旅的首选。"
            ]
        ]
    },
    {
        "name": "乘机流程问题_其他_有效身份证件",
        "intent": [
            "乘机流程问题_其他_有效身份证件"
        ],
        "userinfo": {},
        "action": [
            [
                "reply",
                "有效身份证件包括：中国大陆地区居民的居民身份证、临时居民身份证、护照、军官证、文职干部证、义务兵证、士官证、文职人员证、职工证、武警警官证、武警士兵证、海员证，香港、澳门地区居民的港澳居民来往内地通行证，台湾地区居民的台湾居民来往大陆通行证；外籍旅客的护照、外交部签发的驻华外交人员证、外国人永久居留证；民航局规定的其他有效乘机身份证件。十六周岁以下的中国大陆地区居民的有效乘机身份证件，还包括出生医学证明、户口簿、学生证或户口所在地公安机关出具的身份证明。"
            ]
        ]
    },
    {
        "name": "乘机流程问题_其他_大件行李托运",
        "intent": [
            "乘机流程问题_其他_大件行李托运"
        ],
        "userinfo": {},
        "action": [
            [
                "reply",
                "在登机口、客舱门，工作人员将检查和鉴别您随身携带的行李是否符合要求。如遇超大行李，或遇旅客满员时，工作人员会临时为您的行李办理托运手续。"
            ]
        ]
    },
    {
        "name": "行李问题_携带物品要求_酒类物品携带规定",
        "intent": [
            "行李问题_携带物品要求_酒类物品携带规定"
        ],
        "userinfo": {},
        "action": [
            [
                "reply",
                "在中国境内乘坐民航班机，酒类物品不得随身携带，但可作为托运行李交运。酒类物品的包装应符合民航运输有关规定。其限定条件为：1.标识全面清晰且置于零售包装内，每个容器容积不得超过5L；2.酒精的体积百分含量小于或等于24%时，托运数量不收限制3.酒精的体积腐败分含量大于24%小于或等于70%时，每位旅客托运数量不超过5L。（出自《民航旅客限制随身携带和托运物品目录》）"
            ]
        ]
    },
    {
        "name": "航班问题_其他_航班延误取消解释",
        "intent": [
            "航班问题_其他_航班延误取消解释"
        ],
        "userinfo": {},
        "action": [
            [
                "reply",
                "造成航班不正常的原因通常比较复杂，如天气原因、空中交通管制、机械故障、飞机调配、旅客原因等。在延误补偿方面，需分清责任，区别对待。"
            ]
        ]
    },
    {
        "name": "乘机流程问题_其他_中转服务解释",
        "intent": [
            "乘机流程问题_其他_中转服务解释"
        ],
        "userinfo": {},
        "action": [
            [
                "reply",
                "中转服务是民航针对购买联程机票的旅客而开展的空地一条龙服务。从售票这一环节开始，每个部门都会把中转旅客的姓名，人数、换乘航班情况通知后续部门。中转旅客到达换乘机场后，只要在到达大厅找到中转服务柜台，便会有专人协助其提取行李、办理后续航班登机手续，通过安检。"
            ]
        ]
    },
    {
        "name": "乘机流程问题_其他_登机牌遗失处理方法",
        "intent": [
            "乘机流程问题_其他_登机牌遗失处理方法"
        ],
        "userinfo": {},
        "action": [
            [
                "reply",
                "自己打印的登机牌遗失后，可凭有效证件到机场办理乘机手续柜台补办乘机手续。如果您是在网上自助打印的登机牌，也可凭保存的登机牌图样，重新打印。"
            ]
        ]
    },
    {
        "name": "行李问题_行李托运规则_自助值机托运政策",
        "intent": [
            "行李问题_行李托运规则_自助值机托运政策"
        ],
        "userinfo": {},
        "action": [
            [
                "reply",
                "自助乘机手续一般不能办理行李托运，在机场航空公司会设置行李托运柜台，您可以凭打印的登机牌到柜台托运行李。在机场自助办理乘机手续设备上办理乘机手续后，可以在机场值机柜台补办行李托运手续。要托运行李的旅客请在航班截载前办理（航班截载时间按当地机场公布为准）。"
            ]
        ]
    },
    {
        "name": "航班问题_航班退票改签有航司",
        "intent": [
            "航班问题_航班退票改签有航司"
        ],
        "userinfo": {},
        "action": [
            [
                "reply",
                "意图：航班问题_航班退票改签有航司"
            ]
        ]
    },
    {
        "name": "航班问题_航班号查询航班动态",
        "intent": [
            "航班问题_航班号查询航班动态"
        ],
        "userinfo": {},
        "action": [
            [
                "reply",
                "意图：航班问题_航班号查询航班动态"
            ]
        ]
    },
    {
        "name": "乘机流程问题_出发流程",
        "intent": [
            "乘机流程问题_出发流程"
        ],
        "userinfo": {},
        "action": [
            [
                "reply",
                "1.国内航班出发流程\n2.国际航班出发流程"
            ]
        ]
    },
    {
        "name": "乘机流程问题_到达流程",
        "intent": [
            "乘机流程问题_到达流程"
        ],
        "userinfo": {},
        "action": [
            [
                "reply",
                "1.国内航班到达流程\n2.国际航班到达流程"
            ]
        ]
    },
    {
        "name": "乘机流程问题_乘机证件问题",
        "intent": [
            "乘机流程问题_乘机证件问题"
        ],
        "userinfo": {},
        "action": [
            [
                "reply",
                "您可以咨询\n1.有效身份证件问题\n2.证件过期问题\n3.护照登机政策\n4.临时乘机证明\n5.登机牌遗失处理方法？"
            ]
        ]
    },
    {
        "name": "乘机流程问题_乘机注意事项",
        "intent": [
            "乘机流程问题_乘机注意事项"
        ],
        "userinfo": {},
        "action": [
            [
                "reply",
                "您可以咨询：\n1.乘机安全事项问题\n2.飞行时电子设备使用政策\n3.紧急出口座位规定处理办法"
            ]
        ]
    },
    {
        "name": "乘机流程问题_特殊人群",
        "intent": [
            "乘机流程问题_特殊人群"
        ],
        "userinfo": {},
        "action": [
            [
                "reply",
                "对于因身份、行为、年龄和身体状况等原因，在旅途中需特殊礼遇或照料并符合一定运输条件的旅客，如重要旅客、轮椅旅客、担架旅客、无成人陪伴儿童、老人、盲人、聋人、孕妇等特殊旅客，我们建议您乘机前提前咨询航空公司。您具体想咨询:\n1.残疾旅客服务政策\n2.残障乘客政策\n3.无成人陪伴儿童政策\n4.孕妇乘机政策\n5.军人依法优先政策？"
            ]
        ]
    },
    {
        "name": "航班问题_无航班号查询航班动态",
        "intent": [
            "航班问题_无航班号查询航班动态"
        ],
        "userinfo": {},
        "action": [
            [
                "reply",
                "航班动态详情请咨询航空公司，请问您的航班号是什么，可以给您发一个航空公司的客服电话"
            ]
        ]
    },
    {
        "name": "航班问题_延误或取消后处理方法",
        "intent": [
            "航班问题_延误或取消后处理方法"
        ],
        "userinfo": {},
        "action": [
            [
                "reply",
                "请问您是要咨询：1.航班退票改签\n2.航班延误或取消赔偿政策"
            ]
        ]
    },
    {
        "name": "航班问题_航班退票改签无航司",
        "intent": [
            "航班问题_航班退票改签无航司"
        ],
        "userinfo": {},
        "action": [
            [
                "reply",
                "你可以在线咨询：1.因病退票要求\n2.退款返回方式\n3.经停站退票政策。\n其他不正常航班退改签规则请您咨询航空公司客服，您方便说一下您所乘坐的航空公司吗，我们会告诉您该航空公司的客服电话。"
            ]
        ]
    },
    {
        "name": "票务问题_优惠机票",
        "intent": [
            "票务问题_优惠机票"
        ],
        "userinfo": {},
        "action": [
            [
                "reply",
                "您可以咨询：1.特种票价\n2.特价票政策\n3.伤残军人优惠。如果您购买了特价客票，请您一定要仔细了解航空公司的限制条件（一般是不得退票、不得更改、不得签转），以免造成不必要的损失。"
            ]
        ]
    },
    {
        "name": "票务问题_小孩购票乘机问题",
        "intent": [
            "票务问题_小孩购票乘机问题"
        ],
        "userinfo": {},
        "action": [
            [
                "reply",
                "1.儿童乘机政策\n2.婴儿乘机政策\n3.儿童票价政策？"
            ]
        ]
    },
    {
        "name": "行李问题_行李托运规则",
        "intent": [
            "行李问题_行李托运规则"
        ],
        "userinfo": {},
        "action": [
            [
                "reply",
                "1.托运办理流程\n2.托运办理时间\n3.行李尺寸要求\n4.行李超重问题\n5.托运保价政策\n6.行李丢失损坏漏取问题\n7.自助值机托运政策\n8.托运赔偿额度？"
            ]
        ]
    },
    {
        "name": "行李问题_携带物品要求_可随身携带物品要求",
        "intent": [
            "行李问题_携带物品要求_可随身携带物品要求"
        ],
        "userinfo": {},
        "action": [
            [
                "reply",
                "您在旅行期间可以免费自行携带零星小件物品乘机。每人可携带一件物品，每件的体积不超过20×40×55厘米，重量不超过5公斤。头等舱旅客可以携带2件5公斤。打火机、液体、刀具等不得作为随身携带物品带上飞机。\n1.充电宝\n2.打火机\n3.枪支弹药\n4.化妆品\n5.管制刀具\n6.药品\n7.酒类物品\n8.液体物品\n9.锂电池\n10.其他物品"
            ]
        ]
    },
    {
        "name": "行李问题_携带物品要求_其他物品",
        "intent": [
            "行李问题_携带物品要求_其他物品"
        ],
        "userinfo": {},
        "action": [
            [
                "reply",
                "禁止携带枪支、军用或警用械具类、管制刀具；易燃、易爆物品；毒害品、腐蚀性物品、放射性物品；其他危害飞行安全的物品，如可能干扰飞机上各种仪表正常工作的强磁化物、有强烈刺激性气味的物品等。限带液体生活用品、化妆品。"
            ]
        ]
    }
]
}